taiga/__init__.py
taiga/common/__init__.py
taiga/common/data_handlers.py
taiga/common/data_models.py
taiga/common/fetchers.py
taiga/common/helpers.py
taiga/common/parsers.py
taiga/common/retrievers.py
taiga/core/__init__.py
taiga/core/taxonomy.py
taiga_bio-1.0.4.dist-info/LICENSE
taiga_bio-1.0.4.dist-info/METADATA
taiga_bio-1.0.4.dist-info/WHEEL
taiga_bio-1.0.4.dist-info/top_level.txt
taiga_bio-1.0.4.dist-info/RECORD
