Metadata-Version: 2.1
Name: taiga-bio
Version: 1.0.4
Summary: Set of tools to fetch taxonomic metadata for a list of organisms
Home-page: https://github.com/flayner2/taiga-bio
Author: Maycon Oliveira
Author-email: flayner5@gmail.com
License: UNKNOWN
Platform: UNKNOWN
Classifier: Intended Audience :: Science/Research
Classifier: License :: OSI Approved :: MIT License
Classifier: Operating System :: OS Independent
Classifier: Programming Language :: Python :: 3 :: Only
Classifier: Topic :: Scientific/Engineering :: Bio-Informatics
Requires-Python: >=3.6
Requires-Dist: biopython
Requires-Dist: pandas
